LICENSE
MANIFEST.in
README.rst
setup.py
tibas/__init__.py
tibas.fountain.egg-info/PKG-INFO
tibas.fountain.egg-info/SOURCES.txt
tibas.fountain.egg-info/dependency_links.txt
tibas.fountain.egg-info/namespace_packages.txt
tibas.fountain.egg-info/requires.txt
tibas.fountain.egg-info/top_level.txt
tibas/fountain/__init__.py