Metadata-Version: 1.0
Name: tibas.fountain
Version: 0.1.3
Summary: Sphinx extension for embeding Fountain screenplay fragments
Home-page: bitbucket.org/gabriel.montagne/tibas.fountain
Author: gabriel montangé láscaris-comneno
Author-email: gabriel@tibas.london
License: MIT
Platform: any
